MANIFEST.in
setup.py
votebase/__init__.py
votebase/context_processors.py
votebase/models.py
votebase/settings.py
votebase/urls.py
votebase.egg-info/PKG-INFO
votebase.egg-info/SOURCES.txt
votebase.egg-info/dependency_links.txt
votebase.egg-info/top_level.txt
votebase/core/__init__.py
votebase/core/questionnaires/__init__.py
votebase/core/questionnaires/admin.py
votebase/core/questionnaires/helpers.py
votebase/core/questionnaires/models.py
votebase/core/questionnaires/querysets.py
votebase/core/questionnaires/urls.py
votebase/core/questionnaires/views.py
votebase/core/questionnaires/forms/__init__.py
votebase/core/questionnaires/forms/checkbox.py
votebase/core/questionnaires/forms/dropdown.py
votebase/core/questionnaires/forms/matrix_checkbox.py
votebase/core/questionnaires/forms/matrix_radio.py
votebase/core/questionnaires/forms/radio.py
votebase/core/questionnaires/forms/textarea.py
votebase/core/questionnaires/forms/textfield.py
votebase/core/questionnaires/migrations/0001_initial.py
votebase/core/questionnaires/migrations/0002_option_prefix.py
votebase/core/questionnaires/migrations/0003_auto_20210207_1039.py
votebase/core/questionnaires/migrations/0004_auto_20210207_1045.py
votebase/core/questionnaires/migrations/0005_auto_20210207_1105.py
votebase/core/questionnaires/migrations/0006_auto_20210207_1156.py
votebase/core/questionnaires/migrations/0007_auto_20210208_0202.py
votebase/core/questionnaires/migrations/0008_auto_20210208_0218.py
votebase/core/questionnaires/migrations/0009_survey_tag.py
votebase/core/questionnaires/migrations/0010_auto_20210211_1633.py
votebase/core/questionnaires/migrations/0011_auto_20210211_1641.py
votebase/core/questionnaires/migrations/0012_auto_20220222_1636.py
votebase/core/questionnaires/migrations/0013_auto_20220225_1001.py
votebase/core/questionnaires/migrations/__init__.py
votebase/core/questionnaires/templates/admin/questionnaires/survey/change_form_object_tools.html
votebase/core/questionnaires/templatetags/__init__.py
votebase/core/questionnaires/templatetags/polls_extras.py
votebase/core/statistics/__init__.py
votebase/core/statistics/managers.py
